packageTest/__init__.py
packageTest/packageTest.py
pyjitai/__init__.py
pyjitai/models.py
pyjitai-0.0.0.3.dist-info/METADATA
pyjitai-0.0.0.3.dist-info/WHEEL
pyjitai-0.0.0.3.dist-info/top_level.txt
pyjitai-0.0.0.3.dist-info/RECORD
