Metadata-Version: 2.1
Name: pyjitai
Version: 0.0.0.3
Summary: PyJITAI
Home-page: https://cwphs.ucsd.edu
Author: jup014
Author-email: jup014@ucsd.edu
License: MIT
Platform: UNKNOWN
Requires-Python: >=3
